__init__.py
paycek.py
paycek-1.1.2.dist-info/LICENSE
paycek-1.1.2.dist-info/METADATA
paycek-1.1.2.dist-info/WHEEL
paycek-1.1.2.dist-info/top_level.txt
paycek-1.1.2.dist-info/RECORD
