Metadata-Version: 2.1
Name: paycek
Version: 1.1.2
Summary: A connector library for communicating with PayCek public API
Author: Electrocoin d.o.o.
Project-URL: Website, https://paycek.io
Project-URL: Source Code, https://github.com/electrocoin-eu/paycek-python
Project-URL: Bug Tracker, https://github.com/electrocoin-eu/paycek-python/issues
Keywords: paycek,cryptocurrency,bitcoin,ether,payment,cryptopayment,exchange
Classifier: Programming Language :: Python :: 3
Classifier: License :: OSI Approved :: MIT License
Classifier: Operating System :: OS Independent
Requires-Python: >=3.6
License-File: LICENSE
